key2pane/__init__.py
key2pane/__main__.py
key2pane/cli.py
key2pane/settings.py
key2pane/tmux.py
key2pane-0.0.1.dist-info/LICENSE
key2pane-0.0.1.dist-info/METADATA
key2pane-0.0.1.dist-info/WHEEL
key2pane-0.0.1.dist-info/entry_points.txt
key2pane-0.0.1.dist-info/top_level.txt
key2pane-0.0.1.dist-info/RECORD
