Metadata-Version: 2.1
Name: key2pane
Version: 0.0.1
Summary: Send keys to any tmux pane
Author: BartSte
License: MIT License
Keywords: tmux,key,send,pane,keys,send-keys,send-keys-to-pane,send-keys-to-pane
Classifier: Programming Language :: Python :: 3
Requires-Python: >=3.8
License-File: LICENSE
Provides-Extra: debug
Requires-Dist: ipdb ; extra == 'debug'
Requires-Dist: ipython ; extra == 'debug'
Provides-Extra: test
Requires-Dist: pytest ; extra == 'test'
